opengen/__init__.py
opengen/definitions.py
opengen/builder/__init__.py
opengen/builder/optimizer_builder.py
opengen/builder/problem.py
opengen/builder/ros_builder.py
opengen/builder/set_y_calculator.py
opengen/config/__init__.py
opengen/config/build_config.py
opengen/config/meta.py
opengen/config/ros_config.py
opengen/config/solver_config.py
opengen/config/tcp_server_config.py
opengen/constraints/__init__.py
opengen/constraints/affine_space.py
opengen/constraints/ball1.py
opengen/constraints/ball2.py
opengen/constraints/ball_inf.py
opengen/constraints/cartesian.py
opengen/constraints/constraint.py
opengen/constraints/finite_set.py
opengen/constraints/halfspace.py
opengen/constraints/no_constraints.py
opengen/constraints/rectangle.py
opengen/constraints/simplex.py
opengen/constraints/soc.py
opengen/constraints/sphere2.py
opengen/constraints/zero.py
opengen/functions/__init__.py
opengen/functions/fabs.py
opengen/functions/fmax.py
opengen/functions/fmin.py
opengen/functions/is_numeric.py
opengen/functions/is_symbolic.py
opengen/functions/norm2.py
opengen/functions/norm2_squared.py
opengen/functions/rosenbrock.py
opengen/functions/sign.py
opengen/icasadi/.gitignore
opengen/icasadi/Cargo.toml
opengen/icasadi/README.md
opengen/icasadi/build.rs
opengen/icasadi/extern/README.txt
opengen/icasadi/src/PLACEHOLDER
opengen/tcp/__init__.py
opengen/tcp/optimizer_tcp_manager.py
opengen/tcp/solver_error.py
opengen/tcp/solver_response.py
opengen/tcp/solver_status.py
opengen/templates/cargo_config.toml
opengen/templates/optimizer.rs.jinja
opengen/templates/optimizer_build.rs.jinja
opengen/templates/optimizer_cargo.toml.jinja
opengen/templates/c/example_cmakelists.txt
opengen/templates/c/example_optimizer_c_bindings.c
opengen/templates/c/optimizer_cinterface.rs.jinja
opengen/templates/icasadi/casadi_memory.h
opengen/templates/icasadi/icasadi_cargo.toml
opengen/templates/icasadi/icasadi_lib.rs
opengen/templates/icasadi/interface.c
opengen/templates/python/python_bindings.rs
opengen-0.9.4.dist-info/METADATA
opengen-0.9.4.dist-info/WHEEL
opengen-0.9.4.dist-info/top_level.txt
opengen-0.9.4.dist-info/RECORD
