Metadata-Version: 2.4
Name: opengen
Version: 0.9.4
Summary: Optimization Engine Code Generator
Home-page: https://github.com/alphaville/optimization-engine
Author: ['Pantelis Sopasakis', 'Emil Fresk']
Author-email: xzu.trustful191@passinbox.com
License: MIT License
Keywords: optimization,nonconvex,embedded
Classifier: Development Status :: 4 - Beta
Classifier: License :: OSI Approved :: MIT License
Classifier: License :: OSI Approved :: Apache Software License
Classifier: Programming Language :: Python
Classifier: Programming Language :: Rust
Classifier: Intended Audience :: Science/Research
Classifier: Topic :: Software Development :: Libraries
Classifier: Topic :: Scientific/Engineering
Classifier: Topic :: Scientific/Engineering :: Mathematics
Classifier: Topic :: Software Development :: Code Generators
Classifier: Topic :: Software Development :: Embedded Systems
Requires-Dist: jinja2
Requires-Dist: casadi
Requires-Dist: pyyaml
Requires-Dist: retry
Requires-Dist: numpy
Requires-Dist: setuptools
Dynamic: author
Dynamic: author-email
Dynamic: classifier
Dynamic: description
Dynamic: description-content-type
Dynamic: home-page
Dynamic: keywords
Dynamic: license
Dynamic: requires-dist
Dynamic: summary
